{
  "data": {
    "kind": "guild",
    "hash": 1574506570
  },
  "rollout": {
    "populations": [
      {
        "buckets": {
          "1": {
            "rollout": [
              {
                "start": 0,
                "end": 10000
              }
            ]
          }
        },
        "filters": []
      }
    ],
    "revision": 0,
    "overrides": {
      "1": [
        "281683040739262465",
        "814196235741167637",
        "822219052402606132",
        "21154681615024128",
        "834846951068532756",
        "847184799365857331",
        "862757171887603722"
      ]
    },
    "overrides_formatted": []
  }
}