{
  "id": 215162978,
  "url": "https://hammerandchisel.zendesk.com/api/v2/help_center/en-us/articles/215162978.json",
  "html_url": "https://support.discord.com/hc/en-us/articles/215162978-YouTube-Channel-Memberships-Integration-FAQ",
  "author_id": 2921470028,
  "comments_disabled": true,
  "draft": false,
  "promoted": false,
  "position": 0,
  "section_id": 201110547,
  "created_at": "2015-12-17T23:50:20Z",
  "name": "YouTube Channel Memberships Integration FAQ",
  "title": "YouTube Channel Memberships Integration FAQ",
  "source_locale": "en-us",
  "locale": "en-us",
  "outdated": false,
  "outdated_locales": [],
  "edited_at": "2023-04-21T17:29:33Z",
  "user_segment_id": null,
  "permission_group_id": 1720972,
  "content_tag_ids": [],
  "label_names": [
    "streamer",
    "answer-bot",
    "youtube",
    "youtube integration",
    "youtube connection"
  ]
}